<property name="documentation" class="ptolemy.vergil.basic.DocAttribute">
    <property name="author" class="ptolemy.kernel.util.StringAttribute" value="Hokeun Kim">
    </property>
    <property name="description" class="ptolemy.kernel.util.StringAttribute" value="&lt;p&gt;This accessor is used for publishing secure messages over MQTt protocol,&#10; using authorization service provided by a local authorization entity.&lt;/p&gt;&#10;&lt;p&gt; This accessor requires the &apos;iotAuth&apos; and &apos;mqtt&apos; modules.&lt;/p&gt;">
    </property>
    <property name="toPublish (port)" class="ptolemy.kernel.util.StringAttribute" type="undefined" value="The message to be published.">
    </property>
    <property name="connection (port)" class="ptolemy.kernel.util.StringAttribute" type="undefined" value="Output an object when a connection with a MQTT broker is established.">
    </property>
    <property name="ready (port)" class="ptolemy.kernel.util.StringAttribute" type="undefined" value="Output an object when the secure publisher is ready to publish secure&#10;     messages with a session key and connection with a MQTT broker.">
    </property>
    <property name="brokerHost (parameter)" class="ptolemy.kernel.util.StringAttribute" type="[object Object]" value="The MQTT broker&apos;s IP address or domain name.">
    </property>
    <property name="brokerPort (parameter)" class="ptolemy.kernel.util.StringAttribute" type="[object Object]" value="The MQTT broker&apos;s port number.">
    </property>
    <property name="topic (parameter)" class="ptolemy.kernel.util.StringAttribute" type="[object Object]" value="The topic to publish.">
    </property>
    <property name="qosLevel (parameter)" class="ptolemy.kernel.util.StringAttribute" type="[object Object]" value="QoS level of MQTT for published messages">
    </property>
    <property name="publisherName (parameter)" class="ptolemy.kernel.util.StringAttribute" type="[object Object]" value="The publisher&apos;s unique name in string.">
    </property>
    <property name="authHost (parameter)" class="ptolemy.kernel.util.StringAttribute" type="[object Object]" value="Auth&apos;s IP address or domain name.">
    </property>
    <property name="authPort (parameter)" class="ptolemy.kernel.util.StringAttribute" type="[object Object]" value="Auth&apos;s port number.">
    </property>
    <property name="authCertPath (parameter)" class="ptolemy.kernel.util.StringAttribute" type="[object Object]" value="The path for the X.509 certificate file (in pem format)&#10;  of Auth with which the publisher is registered.">
    </property>
    <property name="publisherPrivateKeyPath (parameter)" class="ptolemy.kernel.util.StringAttribute" type="[object Object]" value="The path for the pem format private key of&#10;  the publisher.">
    </property>
    <property name="publicKeyCryptoSpec (parameter)" class="ptolemy.kernel.util.StringAttribute" type="[object Object]" value="The specification for the public cryptography&#10;  algorithms to be used for communication with Auth">
    </property>
    <property name="distributionCryptoSpec (parameter)" class="ptolemy.kernel.util.StringAttribute" type="[object Object]" value="The specification for the symmetric cryptography&#10;  algorithms to be used for communication with Auth">
    </property>
    <property name="sessionCryptoSpec (parameter)" class="ptolemy.kernel.util.StringAttribute" type="[object Object]" value="The specification for the symmetric cryptography&#10;  algorithms to be used for publishing messages to the subscribers">
    </property>
    <property name="numKeysPerRequest (parameter)" class="ptolemy.kernel.util.StringAttribute" type="[object Object]" value="The number of session keys to be requested per&#10;  session key request to Auth">
    </property>
    <property name="version" class="ptolemy.kernel.util.StringAttribute" value="$$Id$$">
    </property>
</property>